LICENSE.txt
MANIFEST.in
README.rst
setup.cfg
setup.py
reefledge/__init__.py
reefledge/setup.py
reefledge/version.py
reefledge.egg-info/PKG-INFO
reefledge.egg-info/SOURCES.txt
reefledge.egg-info/dependency_links.txt
reefledge.egg-info/not-zip-safe
reefledge.egg-info/requires.txt
reefledge.egg-info/top_level.txt
reefledge/__pycache__/__init__.cpython-310.pyc
reefledge/__pycache__/__init__.cpython-38.pyc
reefledge/__pycache__/__init__.cpython-39.pyc
reefledge/__pycache__/setup.cpython-310.pyc
reefledge/__pycache__/setup.cpython-38.pyc
reefledge/__pycache__/setup.cpython-39.pyc
reefledge/__pycache__/version.cpython-310.pyc
reefledge/__pycache__/version.cpython-38.pyc
reefledge/__pycache__/version.cpython-39.pyc
reefledge/compiled_cython_subpackage/__init__.py
reefledge/compiled_cython_subpackage/manager.py
reefledge/compiled_cython_subpackage/__pycache__/__init__.cpython-310.pyc
reefledge/compiled_cython_subpackage/__pycache__/__init__.cpython-38.pyc
reefledge/compiled_cython_subpackage/__pycache__/__init__.cpython-39.pyc
reefledge/compiled_cython_subpackage/__pycache__/manager.cpython-310.pyc
reefledge/compiled_cython_subpackage/__pycache__/manager.cpython-38.pyc
reefledge/compiled_cython_subpackage/__pycache__/manager.cpython-39.pyc
reefledge/ftp_client/__init__.py
reefledge/ftp_client/base.py
reefledge/ftp_client/isrgrootx1.pem
reefledge/ftp_client/__pycache__/__init__.cpython-310.pyc
reefledge/ftp_client/__pycache__/__init__.cpython-38.pyc
reefledge/ftp_client/__pycache__/__init__.cpython-39.pyc
reefledge/ftp_client/__pycache__/base.cpython-310.pyc
reefledge/ftp_client/__pycache__/base.cpython-38.pyc
reefledge/ftp_client/__pycache__/base.cpython-39.pyc
reefledge/ftp_client/__pycache__/ftp_client.cpython-310.pyc
reefledge/ftp_client/__pycache__/ftp_client.cpython-38.pyc
reefledge/ftp_client/__pycache__/ftp_client.cpython-39.pyc
reefledge/ftp_client/__pycache__/ftp_client_base.cpython-310.pyc
reefledge/ftp_client/__pycache__/ftp_client_base.cpython-38.pyc
reefledge/ftp_client/__pycache__/ftp_client_base.cpython-39.pyc
reefledge/ftp_client/__pycache__/ftp_client_private.cpython-310.pyc
reefledge/ftp_client/__pycache__/ftp_client_private.cpython-38.pyc
