Metadata-Version: 2.1
Name: reefledge
Version: 1.6.1
Summary: A powerful API designed for Quantitative Finance practitioners.
Home-page: https://www.reefledge.com/python_package/docs/
Download-URL: https://github.com/Reefledge/reefledge/archive/refs/tags/v1.6.1.tar.gz
Author: ReefLedge
Author-email: support@reefledge.com
Keywords: quant,quantitative,finance,forecasting,time-series,machine learning,trading,portfolio management,risk management
Platform: Windows
Platform: Linux
Platform: MacOS
Classifier: Development Status :: 5 - Production/Stable
Classifier: Intended Audience :: Developers
Classifier: Operating System :: MacOS
Classifier: Operating System :: MacOS :: MacOS X
Classifier: Operating System :: Microsoft :: Windows
Classifier: Operating System :: Microsoft :: Windows :: Windows 10
Classifier: Operating System :: Microsoft :: Windows :: Windows 11
Classifier: Operating System :: POSIX :: Linux
Classifier: Programming Language :: Python
Classifier: Programming Language :: Python :: 3
Classifier: Programming Language :: Python :: 3.8
Classifier: Programming Language :: Python :: 3.9
Classifier: Programming Language :: Python :: 3.10
Classifier: Topic :: Office/Business :: Financial :: Investment
Classifier: Topic :: Scientific/Engineering :: Artificial Intelligence
Classifier: Typing :: Typed
Classifier: License :: OSI Approved :: MIT License
Requires-Python: >=3.8, <3.11
License-File: LICENSE.txt
